bulksimulator/__init__.py
bulksimulator/bulksimulator.py
bulksimulator/csv_to_pgfplots.py
bulksimulator-0.3.2.dist-info/LICENSE
bulksimulator-0.3.2.dist-info/METADATA
bulksimulator-0.3.2.dist-info/WHEEL
bulksimulator-0.3.2.dist-info/top_level.txt
bulksimulator-0.3.2.dist-info/RECORD
