Metadata-Version: 2.1
Name: bulksimulator
Version: 0.3.2
Summary: Module to run a simulation for many parameter choices
Home-page: https://github.bath.ac.uk/jw3286/bulksimulator
Author: Jeremy Worsfold
Author-email: jw3286@bath.ac.uk
License: GPL3
Platform: UNKNOWN
